ilabs.aclient-0.0.2-nspkg.pth
ilabs/aclient/__init__.py
ilabs/aclient/get_secret.py
ilabs/aclient/ilabs_api.py
ilabs/aclient/ilabs_bulk_predict.py
ilabs/aclient/ilabs_predictor.py
ilabs/aclient/send_request.py
ilabs.aclient-0.0.2.dist-info/LICENSE
ilabs.aclient-0.0.2.dist-info/METADATA
ilabs.aclient-0.0.2.dist-info/WHEEL
ilabs.aclient-0.0.2.dist-info/entry_points.txt
ilabs.aclient-0.0.2.dist-info/namespace_packages.txt
ilabs.aclient-0.0.2.dist-info/top_level.txt
ilabs.aclient-0.0.2.dist-info/RECORD
