Metadata-Version: 2.1
Name: ilabs.aclient
Version: 0.0.2
Summary: Asychronous client to connect to api.innodatalabs.com
Home-page: https://github.com/innodatalabs/ilabs.aclient
Author: Mike Kroutikov
Author-email: mkroutikov@innodata.com
License: MIT
Keywords: innodatalabs api rest async trio
Platform: UNKNOWN
Classifier: Development Status :: 4 - Beta
Classifier: Intended Audience :: Developers
Classifier: License :: OSI Approved :: MIT License
Classifier: Programming Language :: Python :: 3
Classifier: Programming Language :: Python :: 3.6
Classifier: Programming Language :: Python :: 3.7
Classifier: Programming Language :: Python :: 3.8
Classifier: Programming Language :: Python :: Implementation :: CPython
Classifier: Programming Language :: Python :: Implementation :: PyPy
Classifier: Topic :: Software Development :: Libraries :: Python Modules
Requires-Dist: asks (~=2.4.7)
Requires-Dist: trio (~=0.16.0)
